pyinvariant/__init__.py
pyinvariant/empty.cpython-35m-x86_64-linux-gnu.so
pyinvariant/pyinvariant.cpython-35m-x86_64-linux-gnu.so
pyinvariant.libs/libOpenGL-b706661f.so.0.0.0
pyinvariant.libs/libcrypt-57c29b01.so.1.1.0
pyinvariant.libs/libnetcdf-76e33a39.so.18.0.0
pyinvariant.libs/libgssapi_krb5-0f360511.so.2.2
pyinvariant.libs/libidn-97d26f25.so.11.6.11
pyinvariant.libs/libplds4-c7af615d.so
pyinvariant.libs/libnss3-cbdbdc98.so
pyinvariant.libs/libsmime3-42513bb4.so
pyinvariant.libs/libcom_err-64b66bbd.so.2.1
pyinvariant.libs/libplc4-7578b294.so
pyinvariant.libs/liblber-2-76e7e76d.4.so.2.10.7
pyinvariant.libs/libhdf5-ce1fbbb4.so.200.0.0
pyinvariant.libs/libcurl-783997b8.so.4.3.0
pyinvariant.libs/libGLX-404aa684.so.0.0.0
pyinvariant.libs/libssl-84c8c57b.so.1.0.2k
pyinvariant.libs/libjbig-78348776.so.2.0
pyinvariant.libs/libnssutil3-fef13249.so
pyinvariant.libs/libssh2-67280b84.so.1.0.1
pyinvariant.libs/libcrypto-957ef781.so.1.0.2k
pyinvariant.libs/libnspr4-c984c663.so
pyinvariant.libs/libgomp-7c85b1e2.so.1.0.0
pyinvariant.libs/libselinux-0922c95c.so.1
pyinvariant.libs/libldap-2-257051e8.4.so.2.10.7
pyinvariant.libs/libk5crypto-d17c94d0.so.3.1
pyinvariant.libs/libsasl2-05adbfb2.so.3.0.0
pyinvariant.libs/libkrb5support-ec2f3e99.so.0.1
pyinvariant.libs/libhdf5_hl-e57be49e.so.200.0.0
pyinvariant.libs/libGLdispatch-dcc1ca97.so.0.0.0
pyinvariant.libs/libkeyutils-dfe70bd6.so.1.5
pyinvariant.libs/libz-d8a329de.so.1.2.7
pyinvariant.libs/libssl3-16d82696.so
pyinvariant.libs/libpcre-9513aab5.so.1.2.0
pyinvariant.libs/libkrb5-0926b880.so.3.3
pyinvariant.libs/libXt-4e660efc.so.6.0.0
pyinvariant-0.6.dist-info/METADATA
pyinvariant-0.6.dist-info/WHEEL
pyinvariant-0.6.dist-info/top_level.txt
pyinvariant-0.6.dist-info/RECORD
