Metadata-Version: 2.1
Name: pyinvariant
Version: 0.6
Summary: A python interface of the Invariant library
Home-page: https://github.com/ThomasLeMezo/invariant-lib
Author: Thomas Le Mézo
Author-email: thomas.le_mezo@ensta-bretagne.org
License: GPLv3+
Platform: UNKNOWN
Classifier: Development Status :: 3 - Alpha
Classifier: Topic :: Scientific/Engineering :: Mathematics
Classifier: License :: OSI Approved :: GNU General Public License v3 or later (GPLv3+)
Requires-Dist: pyibex (==1.8.1)
